chaosext/__init__.py
chaosext/__version__.py
chaosext/actions.py
chaosext/probes.py
chaostoolkit_extension_template-0.3.0.dist-info/METADATA
chaostoolkit_extension_template-0.3.0.dist-info/WHEEL
chaostoolkit_extension_template-0.3.0.dist-info/licenses/LICENSE
chaostoolkit_extension_template-0.3.0.dist-info/RECORD
